tweetstreamer/__init__.py
tweetstreamer/streamer.py
tweetstreamer-1.0.5.dist-info/LICENSE
tweetstreamer-1.0.5.dist-info/METADATA
tweetstreamer-1.0.5.dist-info/WHEEL
tweetstreamer-1.0.5.dist-info/top_level.txt
tweetstreamer-1.0.5.dist-info/RECORD
