Metadata-Version: 2.1
Name: tweetstreamer
Version: 1.0.5
Summary: A Tweepy streamer to collect tweets from Twitter's Streaming API based on criteria
Home-page: https://github.com/suddi/tweetstreamer
Author: Sudharshan Ravindran
Author-email: mail@suddi.io
License: MIT
Download-URL: https://github.com/suddi/tweetstreamer
Keywords: twitter,streamer,streaming,api,tweet,tweets,tweepy,tweetstream,tweetstreamer
Platform: UNKNOWN
Classifier: Programming Language :: Python :: 3
Classifier: Programming Language :: Python :: 3.8
